Workbook

Sheet README
A1: EXCEL FINANCIAL MODELING & VALUATION TOOLKIT
A2: Dynamic 3-Statement Model · DCF Valuation · Sensitivity & Scenario Analysis · Portfolio Optimization
A4: 1. PURPOSE
A5: This workbook is a modular, fully-dynamic financial modeling and valuation toolkit built to the standard expected
A6: of an investment banking / equity research / private equity analyst. It demonstrates: a linked three-statement
A7: model, a DCF valuation with WACC build-up and two terminal-value methodologies, live two-dimensional sensitivity
A8: tables, a Bear/Base/Bull scenario switch, and a closed-form portfolio-optimization & efficient-frontier module.
A9: Every output is formula-driven from the Assumptions and Scenarios tabs — nothing is hard-coded.
A11: 2. MODEL ARCHITECTURE
A12: README - this tab.
A13: Assumptions - all centralized inputs: company info, BS anchors, historical & forecast operating drivers,
A14: WACC/valuation inputs, and the scenario selector.
... A73: Version 1.0 — built 2026-08-26. Prepared by Maanas (maanas.pabbathi@utexas.edu) for public GitHub publication.

Sheet Assumptions
A1: ASSUMPTIONS — Beacon Industrials, Inc. (BEAC)
A2: All model inputs are centralized here. Blue-fill cells = editable inputs. Black text = formulas. Scenario-linked rows pull from the Scenarios tab based on the selector below.
A4: Company & Model Info
A5: Company Name | B5: Beacon Industrials, Inc.
A6: Ticker | B6: BEAC (fictional / illustrative)
A7: Reporting Currency | B7: USD, $ in millions (except per-share)
A8: Fiscal Year End | B8: December 31
A9: Model Prepared By | B9: Maanas (maanas.pabbathi@utexas.edu)
A10: Model Date | B10: 2026-08-26
A11: Historical Periods | B11: 3 years (FY2023A-FY2025A)
A12: Forecast Periods | B12: 5 years (FY2026E-FY2030E)
A14: Scenario Selector
A15: Active Scenario | B15: Base | C15: (type Bear / Base / Bull — drives Scenarios tab lookups below)
A16: Scenario Index (1=Bear,2=Base,3=Bull) | B16: =MATCH(B15,{"Bear","Base","Bull"},0) -> 2
A18: Balance Sheet Anchors (Beginning of FY2023, $mm)
A19: Beginning Cash | B19: 90
A20: Beginning Net PP&E | B20: 410
A21: Beginning Common Stock / APIC | B21: 250
A22: Beginning Retained Earnings | B22: 18
A23: Beginning Short-Term Debt | B23: 20
A24: Beginning Long-Term Debt | B24: 300
A25: FY2023A Revenue (anchor) | B25: 850
A26: Beginning Accounts Receivable | B26: 119
A27: Beginning Inventory | B27: 76
A28: Beginning Other Current Assets | B28: 24
A29: Beginning Accounts Payable | B29: 64
A30: Beginning Accrued Liabilities | B30: 47
A31: Beginning Other Liabilities | B31: 20
A33: Historical Operating Drivers (flat, FY23A-FY25A)
A34: Revenue Growth % | B34: 0.08
A35: Gross Margin % | B35: 0.41
A36: SG&A % of Revenue | B36: 0.25
A37: D&A % of Revenue | B37: 0.045
A38: Capex % of Revenue | B38: 0.05
A39: Tax Rate % | B39: 0.25
A40: DSO (Days Sales Outstanding) | B40: 55
A41: DIO (Days Inventory Outstanding) | B41: 60
A42: DPO (Days Payable Outstanding) | B42: 50
A43: Other Current Assets % of Revenue | B43: 0.03
A44: Accrued Liabilities % of Revenue | B44: 0.06
A45: Other Liabilities % of Revenue | B45: 0.025
... A48: Diluted Shares Outstanding (mm) | B48: 50
A50: Forecast Operating Drivers (FY2026E-FY2030E)
B51: FY2026E | C51: FY2027E | D51: FY2028E | E51: FY2029E | F51: FY2030E
A52: Revenue Growth % (Y1-Y5) | B52: =CHOOSE(Assumptions!$B$16,Scenarios!$B$8,Scenarios!$C$8,Scenarios!$D$8) -> 0.09 | C52: =CHOOSE(Assumptions!$B$16,Scenarios!$B$9,Scenarios!$C$9,Scenarios!$D$9) -> 0.08 | D52: =CHOOSE(Assumptions!$B$16,Scenarios!$B$10,Scenarios!$C$10,Scenarios!$D$10) -> 0.07 | E52: =CHOOSE(Assumptions!$B$16,Scenarios!$B$11,Scenarios!$C$11,Scenarios!$D$11) -> 0.065 | F52: =CHOOSE(Assumptions!$B$16,Scenarios!$B$12,Scenarios!$C$12,Scenarios!$D$12) -> 0.06
A53: Gross Margin % | B53: =CHOOSE(Assumptions!$B$16,Scenarios!$B$13,Scenarios!$C$13,Scenarios!$D$13) -> 0.415 | C53: (applies to all 5 forecast years; scenario-linked)
A54: SG&A % of Revenue | B54: =CHOOSE(Assumptions!$B$16,Scenarios!$B$14,Scenarios!$C$14,Scenarios!$D$14) -> 0.245 | C54: (applies to all 5 forecast years; scenario-linked)
A55: D&A % of Revenue | B55: =CHOOSE(Assumptions!$B$16,Scenarios!$B$15,Scenarios!$C$15,Scenarios!$D$15) -> 0.045 | C55: (applies to all 5 forecast years; scenario-linked)
A56: Capex % of Revenue | B56: =CHOOSE(Assumptions!$B$16,Scenarios!$B$16,Scenarios!$C$16,Scenarios!$D$16) -> 0.05 | C56: (applies to all 5 forecast years; scenario-linked)
A57: Beta (Levered) | B57: =CHOOSE(Assumptions!$B$16,Scenarios!$B$17,Scenarios!$C$17,Scenarios!$D$17) -> 1.15 | C57: (applies to all 5 forecast years; scenario-linked)
A59: Forecast Operating Drivers (flat / non-scenario)
A60: Tax Rate % | B60: 0.25
A61: DSO (days) | B61: 52
A62: DIO (days) | B62: 58
A63: DPO (days) | B63: 50
A64: Other Current Assets % of Revenue | B64: 0.03
A65: Accrued Liabilities % of Revenue | B65: 0.06
A66: Other Liabilities % of Revenue | B66: 0.025
A67: Interest Rate on Debt % | B67: 0.055
A68: Dividend Payout % of Net Income | B68: 0.25
A69: Debt Issuance / (Repayment) $mm per yr | B69: 0
A70: Diluted Shares Outstanding (mm) | B70: 50
A72: WACC & Valuation Assumptions
A73: Risk-Free Rate | B73: 0.042
A74: Equity Risk Premium | B74: 0.05
A75: Pre-Tax Cost of Debt | B75: 0.065
A76: Target Debt / Total Capital | B76: 0.25
A77: Current Share Price ($) | B77: 42
A78: EV/EBITDA Exit Multiple | B78: 8.5
A79: Terminal Growth Rate (g) | B79: =CHOOSE(Assumptions!$B$16,Scenarios!$B$18,Scenarios!$C$18,Scenarios!$D$18) -> 0.025 | C79: (scenario-linked)

Sheet Scenarios
A1: SCENARIO FRAMEWORK
A2: Bear / Base / Bull assumptions for scenario-sensitive drivers. The Assumptions tab pulls from this table via CHOOSE() based on the Scenario Selector. Edit these cells to change all cases.
A7: Driver | B7: Bear | C7: Base | D7: Bull | E7: Notes
A8: Revenue Growth % - Year 1 | B8: 0.03 | C8: 0.09 | D8: 0.13 | E8: Bear: soft demand; Bull: share gains + pricing
A9: Revenue Growth % - Year 2 | B9: 0.02 | C9: 0.08 | D9: 0.12
A10: Revenue Growth % - Year 3 | B10: 0.02 | C10: 0.07 | D10: 0.11
A11: Revenue Growth % - Year 4 | B11: 0.015 | C11: 0.065 | D11: 0.1
A12: Revenue Growth % - Year 5 | B12: 0.015 | C12: 0.06 | D12: 0.095 | E12: Terminal-approach growth
A13: Gross Margin % | B13: 0.37 | C13: 0.415 | D13: 0.44 | E13: Input cost pressure vs. mix/productivity upside
A14: SG&A % of Revenue | B14: 0.27 | C14: 0.245 | D14: 0.225 | E14: Operating leverage in Bull case
A15: D&A % of Revenue | B15: 0.05 | C15: 0.045 | D15: 0.04 | E15: Capex intensity assumption
A16: Capex % of Revenue | B16: 0.065 | C16: 0.05 | D16: 0.045
A17: Beta (Levered) | B17: 1.35 | C17: 1.15 | D17: 1 | E17: Higher perceived risk in Bear case
A18: Terminal Growth Rate (g) | B18: 0.015 | C18: 0.025 | D18: 0.032 | E18: Must stay below WACC and near long-run GDP growth
A20: How This Feeds The Model
A21: 1. Set Assumptions!B15 to Bear / Base / Bull.
A22: 2. Assumptions tab uses CHOOSE(scenario index, Bear, Base, Bull) to pull the active case.
A23: 3. Every downstream tab (Model, DCF, Sensitivity) recalculates automatically — no other edits needed.
A24: 4. Edit the Bear/Base/Bull columns above to redefine the scenarios themselves.

Sheet Model
A1: THREE-STATEMENT MODEL — Beacon Industrials, Inc. ($mm except per-share)
A2: Historical periods (grey headers) are illustrative/synthetic and formula-driven off Assumptions. Forecast periods (navy headers) flow entirely from Assumptions/Scenarios. No hard-coded outputs.
A4: Line Item | B4: FY2023A | C4: FY2024A | D4: FY2025A | E4: FY2026E | F4: FY2027E | G4: FY2028E | H4: FY2029E | I4: FY2030E
A5: INCOME STATEMENT
A6: Revenue | B6: =Assumptions!$B$25 -> 850 | C6: =B6*(1+Assumptions!$B$34) -> 918 | D6: =C6*(1+Assumptions!$B$34) -> 991.44 | E6: =D6*(1+Assumptions!$B$52) -> 1080.6696 | F6: =E6*(1+Assumptions!$C$52) -> 1167.1232 | G6: =F6*(1+Assumptions!$D$52) -> 1248.8218 | H6: =G6*(1+Assumptions!$E$52) -> 1329.9952 | I6: =H6*(1+Assumptions!$F$52) -> 1409.7949
A7: Revenue Growth % | B7: n/a | C7: =C6/B6-1 -> 0.08 | D7: =D6/C6-1 -> 0.08 | E7: =E6/D6-1 -> 0.09 | F7: =F6/E6-1 -> 0.08 | G7: =G6/F6-1 -> 0.07 | H7: =H6/G6-1 -> 0.065 | I7: =I6/H6-1 -> 0.06
A8: COGS | B8: =B6*(1-Assumptions!$B$35) -> 501.5 | C8: =C6*(1-Assumptions!$B$35) -> 541.62 | D8: =D6*(1-Assumptions!$B$35) -> 584.9496 | E8: =E6*(1-Assumptions!$B$53) -> 632.19172 | F8: =F6*(1-Assumptions!$B$53) -> 682.76705 | G8: =G6*(1-Assumptions!$B$53) -> 730.56075 | H8: =H6*(1-Assumptions!$B$53) -> 778.0472 | I8: =I6*(1-Assumptions!$B$53) -> 824.73003
A9: Gross Profit | B9: =B6-B8 -> 348.5 | C9: =C6-C8 -> 376.38 | D9: =D6-D8 -> 406.4904 | E9: =E6-E8 -> 448.47788 | F9: =F6-F8 -> 484.35611 | G9: =G6-G8 -> 518.26104 | H9: =H6-H8 -> 551.94801 | I9: =I6-I8 -> 585.06489
A10: Gross Margin % | B10: =B9/B6 -> 0.41 | C10: =C9/C6 -> 0.41 | D10: =D9/D6 -> 0.41 | E10: =E9/E6 -> 0.415 | F10: =F9/F6 -> 0.415 | G10: =G9/G6 -> 0.415 | H10: =H9/H6 -> 0.415 | I10: =I9/I6 -> 0.415
A11: SG&A | B11: =B6*Assumptions!$B$36 -> 212.5 | C11: =C6*Assumptions!$B$36 -> 229.5 | D11: =D6*Assumptions!$B$36 -> 247.86 | E11: =E6*Assumptions!$B$54 -> 264.76405 | F11: =F6*Assumptions!$B$54 -> 285.94518 | G11: =G6*Assumptions!$B$54 -> 305.96134 | H11: =H6*Assumptions!$B$54 -> 325.84883 | I11: =I6*Assumptions!$B$54 -> 345.39976
A12: EBITDA | B12: =B9-B11 -> 136 | C12: =C9-C11 -> 146.88 | D12: =D9-D11 -> 158.6304 | E12: =E9-E11 -> 183.71383 | F12: =F9-F11 -> 198.41094 | G12: =G9-G11 -> 212.2997 | H12: =H9-H11 -> 226.09919 | I12: =I9-I11 -> 239.66514
A13: EBITDA Margin % | B13: =B12/B6 -> 0.16 | C13: =C12/C6 -> 0.16 | D13: =D12/D6 -> 0.16 | E13: =E12/E6 -> 0.17 | F13: =F12/F6 -> 0.17 | G13: =G12/G6 -> 0.17 | H13: =H12/H6 -> 0.17 | I13: =I12/I6 -> 0.17
A14: D&A | B14: =B6*Assumptions!$B$37 -> 38.25 | C14: =C6*Assumptions!$B$37 -> 41.31 | D14: =D6*Assumptions!$B$37 -> 44.6148 | E14: =E6*Assumptions!$B$55 -> 48.630132 | F14: =F6*Assumptions!$B$55 -> 52.520543 | G14: =G6*Assumptions!$B$55 -> 56.196981 | H14: =H6*Assumptions!$B$55 -> 59.849784 | I14: =I6*Assumptions!$B$55 -> 63.440771
A15: EBIT | B15: =B12-B14 -> 97.75 | C15: =C12-C14 -> 105.57 | D15: =D12-D14 -> 114.0156 | E15: =E12-E14 -> 135.0837 | F15: =F12-F14 -> 145.8904 | G15: =G12-G14 -> 156.10272 | H15: =H12-H14 -> 166.2494 | I15: =I12-I14 -> 176.22436
A16: Interest Expense | B16: =(Assumptions!$B$23+Assumptions!$B$24)*Assumptions!$B$46 -> 17.6 | C16: =(B34+B35)*Assumptions!$B$46 -> 17.6 | D16: =(C34+C35)*Assumptions!$B$46 -> 17.6 | E16: =(D34+D35)*Assumptions!$B$67 -> 17.6 | F16: =(E34+E35)*Assumptions!$B$67 -> 17.6 | G16: =(F34+F35)*Assumptions!$B$67 -> 17.6 | H16: =(G34+G35)*Assumptions!$B$67 -> 17.6 | I16: =(H34+H35)*Assumptions!$B$67 -> 17.6
A17: EBT | B17: =B15-B16 -> 80.15 | C17: =C15-C16 -> 87.97 | D17: =D15-D16 -> 96.4156 | E17: =E15-E16 -> 117.4837 | F17: =F15-F16 -> 128.2904 | G17: =G15-G16 -> 138.50272 | H17: =H15-H16 -> 148.6494 | I17: =I15-I16 -> 158.62436
A18: Income Taxes | B18: =B17*Assumptions!$B$39 -> 20.0375 | C18: =C17*Assumptions!$B$39 -> 21.9925 | D18: =D17*Assumptions!$B$39 -> 24.1039 | E18: =E17*Assumptions!$B$60 -> 29.370925 | F18: =F17*Assumptions!$B$60 -> 32.072599 | G18: =G17*Assumptions!$B$60 -> 34.625681 | H18: =H17*Assumptions!$B$60 -> 37.16235 | I18: =I17*Assumptions!$B$60 -> 39.656091
A19: Net Income | B19: =B17-B18 -> 60.1125 | C19: =C17-C18 -> 65.9775 | D19: =D17-D18 -> 72.3117 | E19: =E17-E18 -> 88.112775 | F19: =F17-F18 -> 96.217797 | G19: =G17-G18 -> 103.87704 | H19: =H17-H18 -> 111.48705 | I19: =I17-I18 -> 118.96827
A20: Dividends Declared | B20: =B19*Assumptions!$B$47 -> 12.0225 | C20: =C19*Assumptions!$B$47 -> 13.1955 | D20: =D19*Assumptions!$B$47 -> 14.46234 | E20: =E19*Assumptions!$B$68 -> 22.028194 | F20: =F19*Assumptions!$B$68 -> 24.054449 | G20: =G19*Assumptions!$B$68 -> 25.969261 | H20: =H19*Assumptions!$B$68 -> 27.871763 | I20: =I19*Assumptions!$B$68 -> 29.742068
A21: Diluted Shares Outstanding (mm) | B21: =Assumptions!$B$48 -> 50 | C21: =Assumptions!$B$48 -> 50 | D21: =Assumptions!$B$48 -> 50 | E21: =Assumptions!$B$70 -> 50 | F21: =Assumptions!$B$70 -> 50 | G21: =Assumptions!$B$70 -> 50 | H21: =Assumptions!$B$70 -> 50 | I21: =Assumptions!$B$70 -> 50
A22: EPS ($) | B22: =B19/B21 -> 1.20225 | C22: =C19/C21 -> 1.31955 | D22: =D19/D21 -> 1.446234 | E22: =E19/E21 -> 1.7622555 | F22: =F19/F21 -> 1.9243559 | G22: =G19/G21 -> 2.0775409 | H22: =H19/H21 -> 2.229741 | I22: =I19/I21 -> 2.3793655
A24: BALANCE SHEET
A25: Cash & Equivalents | B25: =B61 -> 126.76808 | C25: =C61 -> 167.35433 | D25: =D61 -> 212.03228 | E25: =E61 -> 275.22756 | F25: =F61 -> 332.88506 | G25: =G61 -> 396.35537 | H25: =H61 -> 465.17999 | I25: =I61 -> 539.35429
A26: Accounts Receivable | B26: =B6/365*Assumptions!$B$40 -> 128.08219 | C26: =C6/365*Assumptions!$B$40 -> 138.32877 | D26: =D6/365*Assumptions!$B$40 -> 149.39507 | E26: =E6/365*Assumptions!$B$61 -> 153.95841 | F26: =F6/365*Assumptions!$B$61 -> 166.27508 | G26: =G6/365*Assumptions!$B$61 -> 177.91434 | H26: =H6/365*Assumptions!$B$61 -> 189.47877 | I26: =I6/365*Assumptions!$B$61 -> 200.8475
A27: Inventory | B27: =B8/365*Assumptions!$B$41 -> 82.438356 | C27: =C8/365*Assumptions!$B$41 -> 89.033425 | D27: =D8/365*Assumptions!$B$41 -> 96.156099 | E27: =E8/365*Assumptions!$B$62 -> 100.45786 | F27: =F8/365*Assumptions!$B$62 -> 108.49449 | G27: =G8/365*Assumptions!$B$62 -> 116.08911 | H27: =H8/365*Assumptions!$B$62 -> 123.6349 | I27: =I8/365*Assumptions!$B$62 -> 131.05299
A28: Other Current Assets | B28: =B6*Assumptions!$B$43 -> 25.5 | C28: =C6*Assumptions!$B$43 -> 27.54 | D28: =D6*Assumptions!$B$43 -> 29.7432 | E28: =E6*Assumptions!$B$64 -> 32.420088 | F28: =F6*Assumptions!$B$64 -> 35.013695 | G28: =G6*Assumptions!$B$64 -> 37.464654 | H28: =H6*Assumptions!$B$64 -> 39.899856 | I28: =I6*Assumptions!$B$64 -> 42.293848
A29: Total Current Assets | B29: =SUM(B25:B28) -> 362.78863 | C29: =SUM(C25:C28) -> 422.25652 | D29: =SUM(D25:D28) -> 487.32664 | E29: =SUM(E25:E28) -> 562.06391 | F29: =SUM(F25:F28) -> 642.66833 | G29: =SUM(G25:G28) -> 727.82347 | H29: =SUM(H25:H28) -> 818.19351 | I29: =SUM(I25:I28) -> 913.54862
A30: Net PP&E | B30: =Assumptions!$B$20+B54-B14 -> 414.25 | C30: =B30+C54-C14 -> 418.84 | D30: =C30+D54-D14 -> 423.7972 | E30: =D30+E54-E14 -> 429.20055 | F30: =E30+F54-F14 -> 435.03616 | G30: =F30+G54-G14 -> 441.28027 | H30: =G30+H54-H14 -> 447.93025 | I30: =H30+I54-I14 -> 454.97922
A31: Total Assets | B31: =B29+B30 -> 777.03863 | C31: =C29+C30 -> 841.09652 | D31: =D29+D30 -> 911.12384 | E31: =E29+E30 -> 991.26446 | F31: =F29+F30 -> 1077.7045 | G31: =G29+G30 -> 1169.1037 | H31: =H29+H30 -> 1266.1238 | I31: =I29+I30 -> 1368.5278
A32: Accounts Payable | B32: =B8/365*Assumptions!$B$42 -> 68.69863 | C32: =C8/365*Assumptions!$B$42 -> 74.194521 | D32: =D8/365*Assumptions!$B$42 -> 80.130082 | E32: =E8/365*Assumptions!$B$63 -> 86.601605 | F32: =F8/365*Assumptions!$B$63 -> 93.529733 | G32: =G8/365*Assumptions!$B$63 -> 100.07681 | H32: =H8/365*Assumptions!$B$63 -> 106.58181 | I32: =I8/365*Assumptions!$B$63 -> 112.97672
A33: Accrued Liabilities | B33: =B6*Assumptions!$B$44 -> 51 | C33: =C6*Assumptions!$B$44 -> 55.08 | D33: =D6*Assumptions!$B$44 -> 59.4864 | E33: =E6*Assumptions!$B$65 -> 64.840176 | F33: =F6*Assumptions!$B$65 -> 70.02739 | G33: =G6*Assumptions!$B$65 -> 74.929307 | H33: =H6*Assumptions!$B$65 -> 79.799712 | I33: =I6*Assumptions!$B$65 -> 84.587695
A34: Short-Term Debt | B34: =Assumptions!$B$23 -> 20 | C34: =Assumptions!$B$23 -> 20 | D34: =Assumptions!$B$23 -> 20 | E34: =Assumptions!$B$23 -> 20 | F34: =Assumptions!$B$23 -> 20 | G34: =Assumptions!$B$23 -> 20 | H34: =Assumptions!$B$23 -> 20 | I34: =Assumptions!$B$23 -> 20
A35: Long-Term Debt | B35: =Assumptions!$B$24 -> 300 | C35: =B35 -> 300 | D35: =C35 -> 300 | E35: =D35+Assumptions!$B$69 -> 300 | F35: =E35+Assumptions!$B$69 -> 300 | G35: =F35+Assumptions!$B$69 -> 300 | H35: =G35+Assumptions!$B$69 -> 300 | I35: =H35+Assumptions!$B$69 -> 300
A36: Other Liabilities | B36: =B6*Assumptions!$B$45 -> 21.25 | C36: =C6*Assumptions!$B$45 -> 22.95 | D36: =D6*Assumptions!$B$45 -> 24.786 | E36: =E6*Assumptions!$B$66 -> 27.01674 | F36: =F6*Assumptions!$B$66 -> 29.178079 | G36: =G6*Assumptions!$B$66 -> 31.220545 | H36: =H6*Assumptions!$B$66 -> 33.24988 | I36: =I6*Assumptions!$B$66 -> 35.244873
A37: Total Liabilities | B37: =SUM(B32:B36) -> 460.94863 | C37: =SUM(C32:C36) -> 472.22452 | D37: =SUM(D32:D36) -> 484.40248 | E37: =SUM(E32:E36) -> 498.45852 | F37: =SUM(F32:F36) -> 512.7352 | G37: =SUM(G32:G36) -> 526.22667 | H37: =SUM(H32:H36) -> 539.6314 | I37: =SUM(I32:I36) -> 552.80928
A38: Common Stock & APIC | B38: =Assumptions!$B$21 -> 250 | C38: =Assumptions!$B$21 -> 250 | D38: =Assumptions!$B$21 -> 250 | E38: =Assumptions!$B$21 -> 250 | F38: =Assumptions!$B$21 -> 250 | G38: =Assumptions!$B$21 -> 250 | H38: =Assumptions!$B$21 -> 250 | I38: =Assumptions!$B$21 -> 250
A39: Retained Earnings | B39: =Assumptions!$B$22+B19-B20 -> 66.09 | C39: =B39+C19-C20 -> 118.872 | D39: =C39+D19-D20 -> 176.72136 | E39: =D39+E19-E20 -> 242.80594 | F39: =E39+F19-F20 -> 314.96929 | G39: =F39+G19-G20 -> 392.87707 | H39: =G39+H19-H20 -> 476.49236 | I39: =H39+I19-I20 -> 565.71856
A40: Total Shareholders' Equity | B40: =B38+B39 -> 316.09 | C40: =C38+C39 -> 368.872 | D40: =D38+D39 -> 426.72136 | E40: =E38+E39 -> 492.80594 | F40: =F38+F39 -> 564.96929 | G40: =G38+G39 -> 642.87707 | H40: =H38+H39 -> 726.49236 | I40: =I38+I39 -> 815.71856
A41: Total Liabilities & Equity | B41: =B37+B40 -> 777.03863 | C41: =C37+C40 -> 841.09652 | D41: =D37+D40 -> 911.12384 | E41: =E37+E40 -> 991.26446 | F41: =F37+F40 -> 1077.7045 | G41: =G37+G40 -> 1169.1037 | H41: =H37+H40 -> 1266.1238 | I41: =I37+I40 -> 1368.5278
A42: Balance Check (Assets - L&E) | B42: =B31-B41 -> 0 | C42: =C31-C41 -> 0 | D42: =D31-D41 -> 0 | E42: =E31-E41 -> 0 | F42: =F31-F41 -> 0 | G42: =G31-G41 -> 0 | H42: =H31-H41 -> 0 | I42: =I31-I41 -> 0
A44: CASH FLOW STATEMENT
A45: Net Income | B45: =B19 -> 60.1125 | C45: =C19 -> 65.9775 | D45: =D19 -> 72.3117 | E45: =E19 -> 88.112775 | F45: =F19 -> 96.217797 | G45: =G19 -> 103.87704 | H45: =H19 -> 111.48705 | I45: =I19 -> 118.96827
A46: + D&A | B46: =B14 -> 38.25 | C46: =C14 -> 41.31 | D46: =D14 -> 44.6148 | E46: =E14 -> 48.630132 | F46: =F14 -> 52.520543 | G46: =G14 -> 56.196981 | H46: =H14 -> 59.849784 | I46: =I14 -> 63.440771
A47: (Inc) / Dec in Accounts Receivable | B47: =-(B26-Assumptions!$B$26) -> -9.0821918 | C47: =-(C26-B26) -> -10.246575 | D47: =-(D26-C26) -> -11.066301 | E47: =-(E26-D26) -> -4.5633403 | F47: =-(F26-E26) -> -12.316673 | G47: =-(G26-F26) -> -11.639256 | H47: =-(H26-G26) -> -11.564432 | I47: =-(I26-H26) -> -11.368726
A48: (Inc) / Dec in Inventory | B48: =-(B27-Assumptions!$B$27) -> -6.4383562 | C48: =-(C27-B27) -> -6.5950685 | D48: =-(D27-C27) -> -7.122674 | E48: =-(E27-D27) -> -4.3017631 | F48: =-(F27-E27) -> -8.0366289 | G48: =-(G27-F27) -> -7.5946143 | H48: =-(H27-G27) -> -7.5457918 | I48: =-(I27-H27) -> -7.4180938
A49: (Inc) / Dec in Other Current Assets | B49: =-(B28-Assumptions!$B$28) -> -1.5 | C49: =-(C28-B28) -> -2.04 | D49: =-(D28-C28) -> -2.2032 | E49: =-(E28-D28) -> -2.676888 | F49: =-(F28-E28) -> -2.593607 | G49: =-(G28-F28) -> -2.4509587 | H49: =-(H28-G28) -> -2.4352025 | I49: =-(I28-H28) -> -2.3939914
A50: Inc / (Dec) in Accounts Payable | B50: =(B32-Assumptions!$B$29) -> 4.6986301 | C50: =(C32-B32) -> 5.4958904 | D50: =(D32-C32) -> 5.9355616 | E50: =(E32-D32) -> 6.4715227 | F50: =(F32-E32) -> 6.9281284 | G50: =(G32-F32) -> 6.5470813 | H50: =(H32-G32) -> 6.504993 | I50: =(I32-H32) -> 6.3949085
A51: Inc / (Dec) in Accrued Liabilities | B51: =(B33-Assumptions!$B$30) -> 4 | C51: =(C33-B33) -> 4.08 | D51: =(D33-C33) -> 4.4064 | E51: =(E33-D33) -> 5.353776 | F51: =(F33-E33) -> 5.1872141 | G51: =(G33-F33) -> 4.9019173 | H51: =(H33-G33) -> 4.870405 | I51: =(I33-H33) -> 4.7879827
A52: Inc / (Dec) in Other Liabilities | B52: =(B36-Assumptions!$B$31) -> 1.25 | C52: =(C36-B36) -> 1.7 | D52: =(D36-C36) -> 1.836 | E52: =(E36-D36) -> 2.23074 | F52: =(F36-E36) -> 2.1613392 | G52: =(G36-F36) -> 2.0424655 | H52: =(H36-G36) -> 2.0293354 | I52: =(I36-H36) -> 1.9949928
A53: Cash Flow from Operations | B53: =SUM(B45:B52) -> 91.290582 | C53: =SUM(C45:C52) -> 99.681747 | D53: =SUM(D45:D52) -> 108.71229 | E53: =SUM(E45:E52) -> 139.25695 | F53: =SUM(F45:F52) -> 140.06811 | G53: =SUM(G45:G52) -> 151.88066 | H53: =SUM(H45:H52) -> 163.19614 | I53: =SUM(I45:I52) -> 174.40612
A54: Capital Expenditures | B54: =B6*Assumptions!$B$38 -> 42.5 | C54: =C6*Assumptions!$B$38 -> 45.9 | D54: =D6*Assumptions!$B$38 -> 49.572 | E54: =E6*Assumptions!$B$56 -> 54.03348 | F54: =F6*Assumptions!$B$56 -> 58.356158 | G54: =G6*Assumptions!$B$56 -> 62.441089 | H54: =H6*Assumptions!$B$56 -> 66.49976 | I54: =I6*Assumptions!$B$56 -> 70.489746
A55: Cash Flow from Investing | B55: =-B54 -> -42.5 | C55: =-C54 -> -45.9 | D55: =-D54 -> -49.572 | E55: =-E54 -> -54.03348 | F55: =-F54 -> -58.356158 | G55: =-G54 -> -62.441089 | H55: =-H54 -> -66.49976 | I55: =-I54 -> -70.489746
A56: Debt Issuance / (Repayment) | B56: =0 -> 0 | C56: =0 -> 0 | D56: =0 -> 0 | E56: =Assumptions!$B$69 -> 0 | F56: =Assumptions!$B$69 -> 0 | G56: =Assumptions!$B$69 -> 0 | H56: =Assumptions!$B$69 -> 0 | I56: =Assumptions!$B$69 -> 0
A57: Dividends Paid | B57: =-B20 -> -12.0225 | C57: =-C20 -> -13.1955 | D57: =-D20 -> -14.46234 | E57: =-E20 -> -22.028194 | F57: =-F20 -> -24.054449 | G57: =-G20 -> -25.969261 | H57: =-H20 -> -27.871763 | I57: =-I20 -> -29.742068
A58: Cash Flow from Financing | B58: =B56+B57 -> -12.0225 | C58: =C56+C57 -> -13.1955 | D58: =D56+D57 -> -14.46234 | E58: =E56+E57 -> -22.028194 | F58: =F56+F57 -> -24.054449 | G58: =G56+G57 -> -25.969261 | H58: =H56+H57 -> -27.871763 | I58: =I56+I57 -> -29.742068
A59: Net Change in Cash | B59: =B53+B55+B58 -> 36.768082 | C59: =C53+C55+C58 -> 40.586247 | D59: =D53+D55+D58 -> 44.677946 | E59: =E53+E55+E58 -> 63.195281 | F59: =F53+F55+F58 -> 57.657505 | G59: =G53+G55+G58 -> 63.470309 | H59: =H53+H55+H58 -> 68.824619 | I59: =I53+I55+I58 -> 74.174303
A60: Beginning Cash | B60: =Assumptions!$B$19 -> 90 | C60: =B25 -> 126.76808 | D60: =C25 -> 167.35433 | E60: =D25 -> 212.03228 | F60: =E25 -> 275.22756 | G60: =F25 -> 332.88506 | H60: =G25 -> 396.35537 | I60: =H25 -> 465.17999
A61: Ending Cash | B61: =B60+B59 -> 126.76808 | C61: =C60+C59 -> 167.35433 | D61: =D60+D59 -> 212.03228 | E61: =E60+E59 -> 275.22756 | F61: =F60+F59 -> 332.88506 | G61: =G60+G59 -> 396.35537 | H61: =H60+H59 -> 465.17999 | I61: =I60+I59 -> 539.35429
A63: UNLEVERED FREE CASH FLOW (feeds DCF tab)
A64: Change in Net Working Capital | B64: =-(B47+B48+B49+B50+B51+B52) -> 7.0719178 | C64: =-(C47+C48+C49+C50+C51+C52) -> 7.6057534 | D64: =-(D47+D48+D49+D50+D51+D52) -> 8.2142137 | E64: =-(E47+E48+E49+E50+E51+E52) -> -2.5140474 | F64: =-(F47+F48+F49+F50+F51+F52) -> 8.670227 | G64: =-(G47+G48+G49+G50+G51+G52) -> 8.1933645 | H64: =-(H47+H48+H49+H50+H51+H52) -> 8.1406929 | I64: =-(I47+I48+I49+I50+I51+I52) -> 8.0029273
A65: Unlevered Free Cash Flow (FCFF) | B65: =B15*(1-Assumptions!$B$39)+B14-B54-B64 -> 61.990582 | C65: =C15*(1-Assumptions!$B$39)+C14-C54-C64 -> 66.981747 | D65: =D15*(1-Assumptions!$B$39)+D14-D54-D64 -> 72.340286 | E65: =E15*(1-Assumptions!$B$60)+E14-E54-E64 -> 98.423474 | F65: =F15*(1-Assumptions!$B$60)+F14-F54-F64 -> 94.911954 | G65: =G15*(1-Assumptions!$B$60)+G14-G54-G64 -> 102.63957 | H65: =H15*(1-Assumptions!$B$60)+H14-H54-H64 -> 109.89638 | I65: =I15*(1-Assumptions!$B$60)+I14-I54-I64 -> 117.11637

Sheet DCF
A1: DCF VALUATION — Beacon Industrials, Inc.
A2: Fully dynamic: WACC and FCFF flow from Assumptions/Scenarios and the Model tab. No valuation output below is hard-coded.
A4: WACC Calculation
A5: Risk-Free Rate | B5: =Assumptions!$B$73 -> 0.042
A6: Beta (Levered, scenario-linked) | B6: =Assumptions!$B$57 -> 1.15
A7: Equity Risk Premium | B7: =Assumptions!$B$74 -> 0.05
A8: Cost of Equity (Ke = Rf + β×ERP) | B8: =B5+B6*B7 -> 0.0995
A9: Pre-Tax Cost of Debt | B9: =Assumptions!$B$75 -> 0.065
A10: Tax Rate | B10: =Assumptions!$B$60 -> 0.25
A11: After-Tax Cost of Debt | B11: =B9*(1-B10) -> 0.04875
A12: Target Debt / Total Capital (D/V) | B12: =Assumptions!$B$76 -> 0.25
A13: Target Equity / Total Capital (E/V) | B13: =1-B12 -> 0.75
A14: WACC | B14: =B13*B8+B12*B11 -> 0.0868125
A16: Unlevered Free Cash Flow Projection ($mm)
B17: FY2026E | C17: FY2027E | D17: FY2028E | E17: FY2029E | F17: FY2030E
A18: Discount Period (t) | B18: 1 | C18: 2 | D18: 3 | E18: 4 | F18: 5
A19: FCFF (from Model tab) | B19: =Model!E65 -> 98.423474 | C19: =Model!F65 -> 94.911954 | D19: =Model!G65 -> 102.63957 | E19: =Model!H65 -> 109.89638 | F19: =Model!I65 -> 117.11637
A20: Discount Factor | B20: =1/(1+$B$14)^B18 -> 0.92012192 | C20: =1/(1+$B$14)^C18 -> 0.84662434 | D20: =1/(1+$B$14)^D18 -> 0.77899761 | E20: =1/(1+$B$14)^E18 -> 0.71677277 | F20: =1/(1+$B$14)^F18 -> 0.65951834
A21: PV of FCFF | B21: =B19*B20 -> 90.561596 | C21: =C19*C20 -> 80.354771 | D21: =D19*D20 -> 79.955979 | E21: =E19*E20 -> 78.770734 | F21: =F19*F20 -> 77.240395
A23: Sum of PV of Forecast FCFF | B23: =SUM(B21:F21) -> 406.88347
A25: Terminal Value
A26: Terminal Growth Rate (g) | B26: =Assumptions!$B$79 -> 0.025
A27: Terminal Year FCFF (Y5 × (1+g)) | B27: =F19*(1+B26) -> 120.04428
A28: Terminal Value — Gordon Growth | B28: =B27/($B$14-B26) -> 1942.0713
A29: PV of Terminal Value (Gordon) | B29: =B28*F20 -> 1280.8316
A30: Terminal Year EBITDA (Y5, from Model) | B30: =Model!F12 -> 198.41094
A31: EV / EBITDA Exit Multiple | B31: =Assumptions!$B$78 -> 8.5
A32: Terminal Value — Exit Multiple | B32: =B30*B31 -> 1686.493
A33: PV of Terminal Value (Exit Multiple) | B33: =B32*F20 -> 1112.273
A35: Enterprise Value / Equity Value / Implied Share Price
B36: Gordon Growth Method | C36: Exit Multiple Method
A37: Enterprise Value | B37: =B23+B29 -> 1687.7151 | C37: =B23+B33 -> 1519.1565
A38: (-) Total Debt (current, FY2025A) | B38: =-(Model!D34+Model!D35) -> -320 | C38: =B38 -> -320
A39: (+) Cash & Equivalents (current, FY2025A) | B39: =Model!D25 -> 212.03228 | C39: =B39 -> 212.03228
A40: Equity Value | B40: =B37+B38+B39 -> 1579.7474 | C40: =C37+C38+C39 -> 1411.1888
A41: Diluted Shares Outstanding (mm) | B41: =Model!F21 -> 50 | C41: =B41 -> 50
A42: Implied Share Price | B42: =B40/B41 -> 31.594947 | C42: =C40/C41 -> 28.223776
A43: Current Share Price | B43: =Assumptions!$B$77 -> 42 | C43: =B43 -> 42
A44: Upside / (Downside) | B44: =B42/B43-1 -> -0.24773935 | C44: =C42/C43-1 -> -0.32800534

Sheet Sensitivity
A1: DCF SENSITIVITY ANALYSIS
A2: Every cell below is a self-contained formula (not an Excel What-If Data Table), so results recompute live from the FCFF stream, WACC, and terminal-value assumptions — fully dynamic.
A4: Table 1: Implied Share Price — WACC vs. Terminal Growth Rate (Gordon Growth)
A5: Base case is highlighted.
A6: WACC \ g (down/right) | B6: =DCF!$B$26+(-0.01) -> 0.015 | C6: =DCF!$B$26+(-0.005) -> 0.02 | D6: =DCF!$B$26+(0) -> 0.025 | E6: =DCF!$B$26+(0.005) -> 0.03 | F6: =DCF!$B$26+(0.01) -> 0.035
A7: =DCF!$B$14+(-0.01) -> 0.0768125 | B7: =((DCF!B$19/(1+$A7)^1+DCF!C$19/(1+$A7)^2+DCF!D$19/(1+$A7)^3+DCF!E$19/(1+$A7)^4+DCF!F$19/(1+$A7)^5+(DCF!F$19*(1+B$6))/($A7-B$6)/(1+$A7)^5)-(Model!D34+Model!D35)+Model!D25)/Model!F21 -> 32.769163 | C7: =((DCF!B$19/(1+$A7)^1+DCF!C$19/(1+$A7)^2+DCF!D$19/(1+$A7)^3+DCF!E$19/(1+$A7)^4+DCF!F$19/(1+$A7)^5+(DCF!F$19*(1+C$6))/($A7-C$6)/(1+$A7)^5)-(Model!D34+Model!D35)+Model!D25)/Model!F21 -> 35.24965 | D7: =((DCF!B$19/(1+$A7)^1+DCF!C$19/(1+$A7)^2+DCF!D$19/(1+$A7)^3+DCF!E$19/(1+$A7)^4+DCF!F$19/(1+$A7)^5+(DCF!F$19*(1+D$6))/($A7-D$6)/(1+$A7)^5)-(Model!D34+Model!D35)+Model!D25)/Model!F21 -> 38.208881 | E7: =((DCF!B$19/(1+$A7)^1+DCF!C$19/(1+$A7)^2+DCF!D$19/(1+$A7)^3+DCF!E$19/(1+$A7)^4+DCF!F$19/(1+$A7)^5+(DCF!F$19*(1+E$6))/($A7-E$6)/(1+$A7)^5)-(Model!D34+Model!D35)+Model!D25)/Model!F21 -> 41.800257 | F7: =((DCF!B$19/(1+$A7)^1+DCF!C$19/(1+$A7)^2+DCF!D$19/(1+$A7)^3+DCF!E$19/(1+$A7)^4+DCF!F$19/(1+$A7)^5+(DCF!F$19*(1+F$6))/($A7-F$6)/(1+$A7)^5)-(Model!D34+Model!D35)+Model!D25)/Model!F21 -> 46.250557
A8: =DCF!$B$14+(-0.005) -> 0.0818125 | B8: =((DCF!B$19/(1+$A8)^1+DCF!C$19/(1+$A8)^2+DCF!D$19/(1+$A8)^3+DCF!E$19/(1+$A8)^4+DCF!F$19/(1+$A8)^5+(DCF!F$19*(1+B$6))/($A8-B$6)/(1+$A8)^5)-(Model!D34+Model!D35)+Model!D25)/Model!F21 -> 30.104949 | C8: =((DCF!B$19/(1+$A8)^1+DCF!C$19/(1+$A8)^2+DCF!D$19/(1+$A8)^3+DCF!E$19/(1+$A8)^4+DCF!F$19/(1+$A8)^5+(DCF!F$19*(1+C$6))/($A8-C$6)/(1+$A8)^5)-(Model!D34+Model!D35)+Model!D25)/Model!F21 -> 32.175451 | D8: =((DCF!B$19/(1+$A8)^1+DCF!C$19/(1+$A8)^2+DCF!D$19/(1+$A8)^3+DCF!E$19/(1+$A8)^4+DCF!F$19/(1+$A8)^5+(DCF!F$19*(1+D$6))/($A8-D$6)/(1+$A8)^5)-(Model!D34+Model!D35)+Model!D25)/Model!F21 -> 34.610398 | E8: =((DCF!B$19/(1+$A8)^1+DCF!C$19/(1+$A8)^2+DCF!D$19/(1+$A8)^3+DCF!E$19/(1+$A8)^4+DCF!F$19/(1+$A8)^5+(DCF!F$19*(1+E$6))/($A8-E$6)/(1+$A8)^5)-(Model!D34+Model!D35)+Model!D25)/Model!F21 -> 37.515297 | F8: =((DCF!B$19/(1+$A8)^1+DCF!C$19/(1+$A8)^2+DCF!D$19/(1+$A8)^3+DCF!E$19/(1+$A8)^4+DCF!F$19/(1+$A8)^5+(DCF!F$19*(1+F$6))/($A8-F$6)/(1+$A8)^5)-(Model!D34+Model!D35)+Model!D25)/Model!F21 -> 41.040737
A9: =DCF!$B$14+(0) -> 0.0868125 | B9: =((DCF!B$19/(1+$A9)^1+DCF!C$19/(1+$A9)^2+DCF!D$19/(1+$A9)^3+DCF!E$19/(1+$A9)^4+DCF!F$19/(1+$A9)^5+(DCF!F$19*(1+B$6))/($A9-B$6)/(1+$A9)^5)-(Model!D34+Model!D35)+Model!D25)/Model!F21 -> 27.812676 | C9: =((DCF!B$19/(1+$A9)^1+DCF!C$19/(1+$A9)^2+DCF!D$19/(1+$A9)^3+DCF!E$19/(1+$A9)^4+DCF!F$19/(1+$A9)^5+(DCF!F$19*(1+C$6))/($A9-C$6)/(1+$A9)^5)-(Model!D34+Model!D35)+Model!D25)/Model!F21 -> 29.562286 | D9: =((DCF!B$19/(1+$A9)^1+DCF!C$19/(1+$A9)^2+DCF!D$19/(1+$A9)^3+DCF!E$19/(1+$A9)^4+DCF!F$19/(1+$A9)^5+(DCF!F$19*(1+D$6))/($A9-D$6)/(1+$A9)^5)-(Model!D34+Model!D35)+Model!D25)/Model!F21 -> 31.594947 | E9: =((DCF!B$19/(1+$A9)^1+DCF!C$19/(1+$A9)^2+DCF!D$19/(1+$A9)^3+DCF!E$19/(1+$A9)^4+DCF!F$19/(1+$A9)^5+(DCF!F$19*(1+E$6))/($A9-E$6)/(1+$A9)^5)-(Model!D34+Model!D35)+Model!D25)/Model!F21 -> 33.985393 | F9: =((DCF!B$19/(1+$A9)^1+DCF!C$19/(1+$A9)^2+DCF!D$19/(1+$A9)^3+DCF!E$19/(1+$A9)^4+DCF!F$19/(1+$A9)^5+(DCF!F$19*(1+F$6))/($A9-F$6)/(1+$A9)^5)-(Model!D34+Model!D35)+Model!D25)/Model!F21 -> 36.837204
A10: =DCF!$B$14+(0.005) -> 0.0918125 | B10: =((DCF!B$19/(1+$A10)^1+DCF!C$19/(1+$A10)^2+DCF!D$19/(1+$A10)^3+DCF!E$19/(1+$A10)^4+DCF!F$19/(1+$A10)^5+(DCF!F$19*(1+B$6))/($A10-B$6)/(1+$A10)^5)-(Model!D34+Model!D35)+Model!D25)/Model!F21 -> 25.819687 | C10: =((DCF!B$19/(1+$A10)^1+DCF!C$19/(1+$A10)^2+DCF!D$19/(1+$A10)^3+DCF!E$19/(1+$A10)^4+DCF!F$19/(1+$A10)^5+(DCF!F$19*(1+C$6))/($A10-C$6)/(1+$A10)^5)-(Model!D34+Model!D35)+Model!D25)/Model!F21 -> 27.313834 | D10: =((DCF!B$19/(1+$A10)^1+DCF!C$19/(1+$A10)^2+DCF!D$19/(1+$A10)^3+DCF!E$19/(1+$A10)^4+DCF!F$19/(1+$A10)^5+(DCF!F$19*(1+D$6))/($A10-D$6)/(1+$A10)^5)-(Model!D34+Model!D35)+Model!D25)/Model!F21 -> 29.031614 | E10: =((DCF!B$19/(1+$A10)^1+DCF!C$19/(1+$A10)^2+DCF!D$19/(1+$A10)^3+DCF!E$19/(1+$A10)^4+DCF!F$19/(1+$A10)^5+(DCF!F$19*(1+E$6))/($A10-E$6)/(1+$A10)^5)-(Model!D34+Model!D35)+Model!D25)/Model!F21 -> 31.027296 | F10: =((DCF!B$19/(1+$A10)^1+DCF!C$19/(1+$A10)^2+DCF!D$19/(1+$A10)^3+DCF!E$19/(1+$A10)^4+DCF!F$19/(1+$A10)^5+(DCF!F$19*(1+F$6))/($A10-F$6)/(1+$A10)^5)-(Model!D34+Model!D35)+Model!D25)/Model!F21 -> 33.374254
A11: =DCF!$B$14+(0.01) -> 0.0968125 | B11: =((DCF!B$19/(1+$A11)^1+DCF!C$19/(1+$A11)^2+DCF!D$19/(1+$A11)^3+DCF!E$19/(1+$A11)^4+DCF!F$19/(1+$A11)^5+(DCF!F$19*(1+B$6))/($A11-B$6)/(1+$A11)^5)-(Model!D34+Model!D35)+Model!D25)/Model!F21 -> 24.071091 | C11: =((DCF!B$19/(1+$A11)^1+DCF!C$19/(1+$A11)^2+DCF!D$19/(1+$A11)^3+DCF!E$19/(1+$A11)^4+DCF!F$19/(1+$A11)^5+(DCF!F$19*(1+C$6))/($A11-C$6)/(1+$A11)^5)-(Model!D34+Model!D35)+Model!D25)/Model!F21 -> 25.358856 | D11: =((DCF!B$19/(1+$A11)^1+DCF!C$19/(1+$A11)^2+DCF!D$19/(1+$A11)^3+DCF!E$19/(1+$A11)^4+DCF!F$19/(1+$A11)^5+(DCF!F$19*(1+D$6))/($A11-D$6)/(1+$A11)^5)-(Model!D34+Model!D35)+Model!D25)/Model!F21 -> 26.825943 | E11: =((DCF!B$19/(1+$A11)^1+DCF!C$19/(1+$A11)^2+DCF!D$19/(1+$A11)^3+DCF!E$19/(1+$A11)^4+DCF!F$19/(1+$A11)^5+(DCF!F$19*(1+E$6))/($A11-E$6)/(1+$A11)^5)-(Model!D34+Model!D35)+Model!D25)/Model!F21 -> 28.512614 | F11: =((DCF!B$19/(1+$A11)^1+DCF!C$19/(1+$A11)^2+DCF!D$19/(1+$A11)^3+DCF!E$19/(1+$A11)^4+DCF!F$19/(1+$A11)^5+(DCF!F$19*(1+F$6))/($A11-F$6)/(1+$A11)^5)-(Model!D34+Model!D35)+Model!D25)/Model!F21 -> 30.472153
A14: Table 2: Implied Share Price — WACC vs. EV/EBITDA Exit Multiple
A16: WACC \ Exit Mult. (down/right) | B16: =DCF!$B$31+(-1) -> 7.5 | C16: =DCF!$B$31+(-0.5) -> 8 | D16: =DCF!$B$31+(0) -> 8.5 | E16: =DCF!$B$31+(0.5) -> 9 | F16: =DCF!$B$31+(1) -> 9.5
A17: =DCF!$B$14+(-0.01) -> 0.0768125 | B17: =((DCF!B$19/(1+$A17)^1+DCF!C$19/(1+$A17)^2+DCF!D$19/(1+$A17)^3+DCF!E$19/(1+$A17)^4+DCF!F$19/(1+$A17)^5+(DCF!$B$30*B$16)/(1+$A17)^5)-(Model!D34+Model!D35)+Model!D25)/Model!F21 -> 26.75935 | C17: =((DCF!B$19/(1+$A17)^1+DCF!C$19/(1+$A17)^2+DCF!D$19/(1+$A17)^3+DCF!E$19/(1+$A17)^4+DCF!F$19/(1+$A17)^5+(DCF!$B$30*C$16)/(1+$A17)^5)-(Model!D34+Model!D35)+Model!D25)/Model!F21 -> 28.129806 | D17: =((DCF!B$19/(1+$A17)^1+DCF!C$19/(1+$A17)^2+DCF!D$19/(1+$A17)^3+DCF!E$19/(1+$A17)^4+DCF!F$19/(1+$A17)^5+(DCF!$B$30*D$16)/(1+$A17)^5)-(Model!D34+Model!D35)+Model!D25)/Model!F21 -> 29.500262 | E17: =((DCF!B$19/(1+$A17)^1+DCF!C$19/(1+$A17)^2+DCF!D$19/(1+$A17)^3+DCF!E$19/(1+$A17)^4+DCF!F$19/(1+$A17)^5+(DCF!$B$30*E$16)/(1+$A17)^5)-(Model!D34+Model!D35)+Model!D25)/Model!F21 -> 30.870719 | F17: =((DCF!B$19/(1+$A17)^1+DCF!C$19/(1+$A17)^2+DCF!D$19/(1+$A17)^3+DCF!E$19/(1+$A17)^4+DCF!F$19/(1+$A17)^5+(DCF!$B$30*F$16)/(1+$A17)^5)-(Model!D34+Model!D35)+Model!D25)/Model!F21 -> 32.241175
A18: =DCF!$B$14+(-0.005) -> 0.0818125 | B18: =((DCF!B$19/(1+$A18)^1+DCF!C$19/(1+$A18)^2+DCF!D$19/(1+$A18)^3+DCF!E$19/(1+$A18)^4+DCF!F$19/(1+$A18)^5+(DCF!$B$30*B$16)/(1+$A18)^5)-(Model!D34+Model!D35)+Model!D25)/Model!F21 -> 26.17537 | C18: =((DCF!B$19/(1+$A18)^1+DCF!C$19/(1+$A18)^2+DCF!D$19/(1+$A18)^3+DCF!E$19/(1+$A18)^4+DCF!F$19/(1+$A18)^5+(DCF!$B$30*C$16)/(1+$A18)^5)-(Model!D34+Model!D35)+Model!D25)/Model!F21 -> 27.514447 | D18: =((DCF!B$19/(1+$A18)^1+DCF!C$19/(1+$A18)^2+DCF!D$19/(1+$A18)^3+DCF!E$19/(1+$A18)^4+DCF!F$19/(1+$A18)^5+(DCF!$B$30*D$16)/(1+$A18)^5)-(Model!D34+Model!D35)+Model!D25)/Model!F21 -> 28.853524 | E18: =((DCF!B$19/(1+$A18)^1+DCF!C$19/(1+$A18)^2+DCF!D$19/(1+$A18)^3+DCF!E$19/(1+$A18)^4+DCF!F$19/(1+$A18)^5+(DCF!$B$30*E$16)/(1+$A18)^5)-(Model!D34+Model!D35)+Model!D25)/Model!F21 -> 30.192601 | F18: =((DCF!B$19/(1+$A18)^1+DCF!C$19/(1+$A18)^2+DCF!D$19/(1+$A18)^3+DCF!E$19/(1+$A18)^4+DCF!F$19/(1+$A18)^5+(DCF!$B$30*F$16)/(1+$A18)^5)-(Model!D34+Model!D35)+Model!D25)/Model!F21 -> 31.531679
A19: =DCF!$B$14+(0) -> 0.0868125 | B19: =((DCF!B$19/(1+$A19)^1+DCF!C$19/(1+$A19)^2+DCF!D$19/(1+$A19)^3+DCF!E$19/(1+$A19)^4+DCF!F$19/(1+$A19)^5+(DCF!$B$30*B$16)/(1+$A19)^5)-(Model!D34+Model!D35)+Model!D25)/Model!F21 -> 25.606663 | C19: =((DCF!B$19/(1+$A19)^1+DCF!C$19/(1+$A19)^2+DCF!D$19/(1+$A19)^3+DCF!E$19/(1+$A19)^4+DCF!F$19/(1+$A19)^5+(DCF!$B$30*C$16)/(1+$A19)^5)-(Model!D34+Model!D35)+Model!D25)/Model!F21 -> 26.915219 | D19: =((DCF!B$19/(1+$A19)^1+DCF!C$19/(1+$A19)^2+DCF!D$19/(1+$A19)^3+DCF!E$19/(1+$A19)^4+DCF!F$19/(1+$A19)^5+(DCF!$B$30*D$16)/(1+$A19)^5)-(Model!D34+Model!D35)+Model!D25)/Model!F21 -> 28.223776 | E19: =((DCF!B$19/(1+$A19)^1+DCF!C$19/(1+$A19)^2+DCF!D$19/(1+$A19)^3+DCF!E$19/(1+$A19)^4+DCF!F$19/(1+$A19)^5+(DCF!$B$30*E$16)/(1+$A19)^5)-(Model!D34+Model!D35)+Model!D25)/Model!F21 -> 29.532332 | F19: =((DCF!B$19/(1+$A19)^1+DCF!C$19/(1+$A19)^2+DCF!D$19/(1+$A19)^3+DCF!E$19/(1+$A19)^4+DCF!F$19/(1+$A19)^5+(DCF!$B$30*F$16)/(1+$A19)^5)-(Model!D34+Model!D35)+Model!D25)/Model!F21 -> 30.840889
A20: =DCF!$B$14+(0.005) -> 0.0918125 | B20: =((DCF!B$19/(1+$A20)^1+DCF!C$19/(1+$A20)^2+DCF!D$19/(1+$A20)^3+DCF!E$19/(1+$A20)^4+DCF!F$19/(1+$A20)^5+(DCF!$B$30*B$16)/(1+$A20)^5)-(Model!D34+Model!D35)+Model!D25)/Model!F21 -> 25.052756 | C20: =((DCF!B$19/(1+$A20)^1+DCF!C$19/(1+$A20)^2+DCF!D$19/(1+$A20)^3+DCF!E$19/(1+$A20)^4+DCF!F$19/(1+$A20)^5+(DCF!$B$30*C$16)/(1+$A20)^5)-(Model!D34+Model!D35)+Model!D25)/Model!F21 -> 26.331622 | D20: =((DCF!B$19/(1+$A20)^1+DCF!C$19/(1+$A20)^2+DCF!D$19/(1+$A20)^3+DCF!E$19/(1+$A20)^4+DCF!F$19/(1+$A20)^5+(DCF!$B$30*D$16)/(1+$A20)^5)-(Model!D34+Model!D35)+Model!D25)/Model!F21 -> 27.610489 | E20: =((DCF!B$19/(1+$A20)^1+DCF!C$19/(1+$A20)^2+DCF!D$19/(1+$A20)^3+DCF!E$19/(1+$A20)^4+DCF!F$19/(1+$A20)^5+(DCF!$B$30*E$16)/(1+$A20)^5)-(Model!D34+Model!D35)+Model!D25)/Model!F21 -> 28.889356 | F20: =((DCF!B$19/(1+$A20)^1+DCF!C$19/(1+$A20)^2+DCF!D$19/(1+$A20)^3+DCF!E$19/(1+$A20)^4+DCF!F$19/(1+$A20)^5+(DCF!$B$30*F$16)/(1+$A20)^5)-(Model!D34+Model!D35)+Model!D25)/Model!F21 -> 30.168223
A21: =DCF!$B$14+(0.01) -> 0.0968125 | B21: =((DCF!B$19/(1+$A21)^1+DCF!C$19/(1+$A21)^2+DCF!D$19/(1+$A21)^3+DCF!E$19/(1+$A21)^4+DCF!F$19/(1+$A21)^5+(DCF!$B$30*B$16)/(1+$A21)^5)-(Model!D34+Model!D35)+Model!D25)/Model!F21 -> 24.513191 | C21: =((DCF!B$19/(1+$A21)^1+DCF!C$19/(1+$A21)^2+DCF!D$19/(1+$A21)^3+DCF!E$19/(1+$A21)^4+DCF!F$19/(1+$A21)^5+(DCF!$B$30*C$16)/(1+$A21)^5)-(Model!D34+Model!D35)+Model!D25)/Model!F21 -> 25.763172 | D21: =((DCF!B$19/(1+$A21)^1+DCF!C$19/(1+$A21)^2+DCF!D$19/(1+$A21)^3+DCF!E$19/(1+$A21)^4+DCF!F$19/(1+$A21)^5+(DCF!$B$30*D$16)/(1+$A21)^5)-(Model!D34+Model!D35)+Model!D25)/Model!F21 -> 27.013154 | E21: =((DCF!B$19/(1+$A21)^1+DCF!C$19/(1+$A21)^2+DCF!D$19/(1+$A21)^3+DCF!E$19/(1+$A21)^4+DCF!F$19/(1+$A21)^5+(DCF!$B$30*E$16)/(1+$A21)^5)-(Model!D34+Model!D35)+Model!D25)/Model!F21 -> 28.263136 | F21: =((DCF!B$19/(1+$A21)^1+DCF!C$19/(1+$A21)^2+DCF!D$19/(1+$A21)^3+DCF!E$19/(1+$A21)^4+DCF!F$19/(1+$A21)^5+(DCF!$B$30*F$16)/(1+$A21)^5)-(Model!D34+Model!D35)+Model!D25)/Model!F21 -> 29.513117
A24: Scenario Output Log (toggle Assumptions!B15 and record results)
A25: Scenario | B25: Implied Price (Gordon) | C25: Implied Price (Exit Mult.) | D25: EV ($mm) | E25: WACC | F25: Notes
A26: Bear
A27: Base (current)
A28: Bull
A29: Tip: set Assumptions!B15 to each case, then paste values from DCF!B42 (Gordon) / DCF!C42 (Exit Mult.) into this log.

Sheet Portfolio
A1: PORTFOLIO OPTIMIZATION & RISK ANALYTICS
A2: Illustrative synthetic monthly total-return data (NOT real market data) for a 5-asset universe. All statistics, weights, and the efficient frontier recompute live from the return series below.
A4: Monthly Total Returns (synthetic, 36 months)
A5: Month | B5: TechCo | C5: HealthCo | D5: EnergyCo | E5: ConsumerCo | F5: FinCo | H5: Port. Monthly Ret. | I5: Wealth Index | J5: Running Max | K5: Drawdown
A6: Month 1 | B6: 0.0468 | C6: 0.01 | D6: 0.0498 | E6: 0.0799 | F6: 0.0277 | H6: =SUMPRODUCT($B$66:$F$66,B6:F6) -> 0.04284 | I6: =1*(1+H6) -> 1.04284 | J6: =I6 -> 1.04284 | K6: =I6/J6-1 -> 0
A7: Month 2 | B7: -0.0044 | C7: 0.0709 | D7: 0.0581 | E7: 0.0132 | F7: 0.0456 | H7: =SUMPRODUCT($B$66:$F$66,B7:F7) -> 0.03668 | I7: =I6*(1+H7) -> 1.0810914 | J7: =MAX(J6,I7) -> 1.0810914 | K7: =I7/J7-1 -> 0
A8: Month 3 | B8: -0.0204 | C8: -0.0189 | D8: 0.0096 | E8: -0.0923 | F8: -0.1059 | H8: =SUMPRODUCT($B$66:$F$66,B8:F8) -> -0.04558 | I8: =I7*(1+H8) -> 1.0318152 | J8: =MAX(J7,I8) -> 1.0810914 | K8: =I8/J8-1 -> -0.04558
A9: Month 4 | B9: -0.0274 | C9: -0.0436 | D9: 0.0084 | E9: -0.0595 | F9: -0.0874 | H9: =SUMPRODUCT($B$66:$F$66,B9:F9) -> -0.0419 | I9: =I8*(1+H9) -> 0.98858217 | J9: =MAX(J8,I9) -> 1.0810914 | K9: =I9/J9-1 -> -0.085570198
A10: Month 5 | B10: 0.1146 | C10: 0.0216 | D10: 0.0303 | E10: -0.0377 | F10: -0.001 | H10: =SUMPRODUCT($B$66:$F$66,B10:F10) -> 0.02556 | I10: =I9*(1+H10) -> 1.0138503 | J10: =MAX(J9,I10) -> 1.0810914 | K10: =I10/J10-1 -> -0.062197372
A11: Month 6 | B11: 0.0198 | C11: -0.0388 | D11: 0.021 | E11: -0.0383 | F11: -0.0167 | H11: =SUMPRODUCT($B$66:$F$66,B11:F11) -> -0.0106 | I11: =I10*(1+H11) -> 1.0031035 | J11: =MAX(J10,I11) -> 1.0810914 | K11: =I11/J11-1 -> -0.07213808
A12: Month 7 | B12: -0.0301 | C12: 0.0766 | D12: 0.0095 | E12: -0.0144 | F12: 0.0417 | H12: =SUMPRODUCT($B$66:$F$66,B12:F12) -> 0.01666 | I12: =I11*(1+H12) -> 1.0198152 | J12: =MAX(J11,I12) -> 1.0810914 | K12: =I12/J12-1 -> -0.056679901
A13: Month 8 | B13: -0.0735 | C13: -0.0024 | D13: -0.1238 | E13: -0.069 | F13: -0.0345 | H13: =SUMPRODUCT($B$66:$F$66,B13:F13) -> -0.06064 | I13: =I12*(1+H13) -> 0.95797362 | J13: =MAX(J12,I13) -> 1.0810914 | K13: =I13/J13-1 -> -0.11388283
A14: Month 9 | B14: 0.0637 | C14: 0.0269 | D14: 0.0116 | E14: 0.0078 | F14: -0.0479 | H14: =SUMPRODUCT($B$66:$F$66,B14:F14) -> 0.01242 | I14: =I13*(1+H14) -> 0.96987166 | J14: =MAX(J13,I14) -> 1.0810914 | K14: =I14/J14-1 -> -0.10287726
A15: Month 10 | B15: -0.0384 | C15: -0.0228 | D15: 0.0528 | E15: 0.0045 | F15: -0.0843 | H15: =SUMPRODUCT($B$66:$F$66,B15:F15) -> -0.01764 | I15: =I14*(1+H15) -> 0.95276312 | J15: =MAX(J14,I15) -> 1.0810914 | K15: =I15/J15-1 -> -0.1187025
A16: Month 11 | B16: 0.0347 | C16: -0.0031 | D16: -0.0309 | E16: 0.0306 | F16: 0.0631 | H16: =SUMPRODUCT($B$66:$F$66,B16:F16) -> 0.01888 | I16: =I15*(1+H16) -> 0.97075129 | J16: =MAX(J15,I16) -> 1.0810914 | K16: =I16/J16-1 -> -0.1020636
A17: Month 12 | B17: 0.0772 | C17: -0.0127 | D17: -0.0039 | E17: 0.0196 | F17: 0.0694 | H17: =SUMPRODUCT($B$66:$F$66,B17:F17) -> 0.02992 | I17: =I16*(1+H17) -> 0.99979617 | J17: =MAX(J16,I17) -> 1.0810914 | K17: =I17/J17-1 -> -0.075197348
A18: Month 13 | B18: -0.0215 | C18: -0.0074 | D18: -0.0663 | E18: -0.058 | F18: 0.0153 | H18: =SUMPRODUCT($B$66:$F$66,B18:F18) -> -0.02758 | I18: =I17*(1+H18) -> 0.97222179 | J18: =MAX(J17,I18) -> 1.0810914 | K18: =I18/J18-1 -> -0.1007034
... A41: Month 36 | B41: 0.0699 | C41: 0.0216 | D41: 0.1023 | E41: 0.0103 | F41: 0.1657 | H41: =SUMPRODUCT($B$66:$F$66,B41:F41) -> 0.07396 | I41: =I40*(1+H41) -> 1.3227968 | J41: =MAX(J40,I41) -> 1.3227968 | K41: =I41/J41-1 -> 0
A43: Annualized Return & Risk by Asset
B44: TechCo | C44: HealthCo | D44: EnergyCo | E44: ConsumerCo | F44: FinCo
A45: Annualized Return | B45: =AVERAGE($B$6:$B$41)*12 -> 0.15593333 | C45: =AVERAGE($C$6:$C$41)*12 -> 0.1678 | D45: =AVERAGE($D$6:$D$41)*12 -> 0.10166667 | E45: =AVERAGE($E$6:$E$41)*12 -> 0.059466667 | F45: =AVERAGE($F$6:$F$41)*12 -> 0.015566667
A46: Annualized Volatility | B46: =STDEV($B$6:$B$41)*SQRT(12) -> 0.2325716 | C46: =STDEV($C$6:$C$41)*SQRT(12) -> 0.13040058 | D46: =STDEV($D$6:$D$41)*SQRT(12) -> 0.19370411 | E46: =STDEV($E$6:$E$41)*SQRT(12) -> 0.15912911 | F46: =STDEV($F$6:$F$41)*SQRT(12) -> 0.18842396
A48: Annualized Covariance Matrix
B49: TechCo | C49: HealthCo | D49: EnergyCo | E49: ConsumerCo | F49: FinCo
A50: TechCo | B50: =_xlfn.COVARIANCE.P($B$6:$B$41,$B$6:$B$41)*12 -> 0.05258706 | C50: =_xlfn.COVARIANCE.P($B$6:$B$41,$C$6:$C$41)*12 -> 0.0052664656 | D50: =_xlfn.COVARIANCE.P($B$6:$B$41,$D$6:$D$41)*12 -> 0.012639045 | E50: =_xlfn.COVARIANCE.P($B$6:$B$41,$E$6:$E$41)*12 -> 0.01107504 | F50: =_xlfn.COVARIANCE.P($B$6:$B$41,$F$6:$F$41)*12 -> 0.013754533
A51: HealthCo | B51: =_xlfn.COVARIANCE.P($C$6:$C$41,$B$6:$B$41)*12 -> 0.0052664656 | C51: =_xlfn.COVARIANCE.P($C$6:$C$41,$C$6:$C$41)*12 -> 0.01653197 | D51: =_xlfn.COVARIANCE.P($C$6:$C$41,$D$6:$D$41)*12 -> 0.0064954378 | E51: =_xlfn.COVARIANCE.P($C$6:$C$41,$E$6:$E$41)*12 -> 0.0076858678 | F51: =_xlfn.COVARIANCE.P($C$6:$C$41,$F$6:$F$41)*12 -> 0.0067549694
A52: EnergyCo | B52: =_xlfn.COVARIANCE.P($D$6:$D$41,$B$6:$B$41)*12 -> 0.012639045 | C52: =_xlfn.COVARIANCE.P($D$6:$D$41,$C$6:$C$41)*12 -> 0.0064954378 | D52: =_xlfn.COVARIANCE.P($D$6:$D$41,$D$6:$D$41)*12 -> 0.036479024 | E52: =_xlfn.COVARIANCE.P($D$6:$D$41,$E$6:$E$41)*12 -> 0.0021330785 | F52: =_xlfn.COVARIANCE.P($D$6:$D$41,$F$6:$F$41)*12 -> 0.0074346624
A53: ConsumerCo | B53: =_xlfn.COVARIANCE.P($E$6:$E$41,$B$6:$B$41)*12 -> 0.01107504 | C53: =_xlfn.COVARIANCE.P($E$6:$E$41,$C$6:$C$41)*12 -> 0.0076858678 | D53: =_xlfn.COVARIANCE.P($E$6:$E$41,$D$6:$D$41)*12 -> 0.0021330785 | E53: =_xlfn.COVARIANCE.P($E$6:$E$41,$E$6:$E$41)*12 -> 0.024618683 | F53: =_xlfn.COVARIANCE.P($E$6:$E$41,$F$6:$F$41)*12 -> 0.0060248252
A54: FinCo | B54: =_xlfn.COVARIANCE.P($F$6:$F$41,$B$6:$B$41)*12 -> 0.013754533 | C54: =_xlfn.COVARIANCE.P($F$6:$F$41,$C$6:$C$41)*12 -> 0.0067549694 | D54: =_xlfn.COVARIANCE.P($F$6:$F$41,$D$6:$D$41)*12 -> 0.0074346624 | E54: =_xlfn.COVARIANCE.P($F$6:$F$41,$E$6:$E$41)*12 -> 0.0060248252 | F54: =_xlfn.COVARIANCE.P($F$6:$F$41,$F$6:$F$41)*12 -> 0.034517377
A56: Correlation Matrix
B57: TechCo | C57: HealthCo | D57: EnergyCo | E57: ConsumerCo | F57: FinCo
A58: TechCo | B58: =CORREL($B$6:$B$41,$B$6:$B$41) -> 1 | C58: =CORREL($B$6:$B$41,$C$6:$C$41) -> 0.17861482 | D58: =CORREL($B$6:$B$41,$D$6:$D$41) -> 0.28857135 | E58: =CORREL($B$6:$B$41,$E$6:$E$41) -> 0.30780344 | F58: =CORREL($B$6:$B$41,$F$6:$F$41) -> 0.32284013
A59: HealthCo | B59: =CORREL($C$6:$C$41,$B$6:$B$41) -> 0.17861482 | C59: =CORREL($C$6:$C$41,$C$6:$C$41) -> 1 | D59: =CORREL($C$6:$C$41,$D$6:$D$41) -> 0.26449929 | E59: =CORREL($C$6:$C$41,$E$6:$E$41) -> 0.38097651 | F59: =CORREL($C$6:$C$41,$F$6:$F$41) -> 0.28277577
A60: EnergyCo | B60: =CORREL($D$6:$D$41,$B$6:$B$41) -> 0.28857135 | C60: =CORREL($D$6:$D$41,$C$6:$C$41) -> 0.26449929 | D60: =CORREL($D$6:$D$41,$D$6:$D$41) -> 1 | E60: =CORREL($D$6:$D$41,$E$6:$E$41) -> 0.071179155 | F60: =CORREL($D$6:$D$41,$F$6:$F$41) -> 0.20951772
A61: ConsumerCo | B61: =CORREL($E$6:$E$41,$B$6:$B$41) -> 0.30780344 | C61: =CORREL($E$6:$E$41,$C$6:$C$41) -> 0.38097651 | D61: =CORREL($E$6:$E$41,$D$6:$D$41) -> 0.071179155 | E61: =CORREL($E$6:$E$41,$E$6:$E$41) -> 1 | F61: =CORREL($E$6:$E$41,$F$6:$F$41) -> 0.20667748
A62: FinCo | B62: =CORREL($F$6:$F$41,$B$6:$B$41) -> 0.32284013 | C62: =CORREL($F$6:$F$41,$C$6:$C$41) -> 0.28277577 | D62: =CORREL($F$6:$F$41,$D$6:$D$41) -> 0.20951772 | E62: =CORREL($F$6:$F$41,$E$6:$E$41) -> 0.20667748 | F62: =CORREL($F$6:$F$41,$F$6:$F$41) -> 1
A64: User Portfolio (editable weights)
B65: TechCo | C65: HealthCo | D65: EnergyCo | E65: ConsumerCo | F65: FinCo
A66: Portfolio Weight | B66: 0.2 | C66: 0.2 | D66: 0.2 | E66: 0.2 | F66: 0.2
A67: Sum of Weights (must = 100%) | B67: =SUM(B66:F66) -> 1
A68: Risk-Free Rate (for Sharpe) | B68: =Assumptions!$B$73 -> 0.042
A69: Portfolio Expected Return | B69: =SUMPRODUCT(B66:F66,$B$45:$F$45) -> 0.10008667
A70: Portfolio Variance | B70: {=MMULT(MMULT(B66:F66,$B$50:$F$54),TRANSPOSE(B66:F66))} -> 0.012930479
A71: Portfolio Volatility | B71: =SQRT(B70) -> 0.11371226
A72: Sharpe Ratio | B72: =(B69-B68)/B71 -> 0.51082149
A73: Max Drawdown (from monthly series) | B73: =MIN(K6:K41) -> -0.1187025
A75: Closed-Form Optimization Vectors (Merton 1972 unconstrained frontier)
A76: Asset | B76: mu (vertical) | C76: Ones | D76: u = Σ⁻¹·1 | E76: v = Σ⁻¹·μ
A77: TechCo | B77: =B45 -> 0.15593333 | C77: 1 | D77: {=MMULT(MINVERSE($B$50:$F$54),$C$77:$C$81)} -> 3.2894888 | E77: {=MMULT(MINVERSE($B$50:$F$54),$B$77:$B$81)} -> 2.7800727
A78: HealthCo | B78: =C45 -> 0.1678 | C78: 1 | D78: 37.318856 | E78: 10.893513
A79: EnergyCo | B79: =D45 -> 0.10166667 | C79: 1 | D79: 15.640284 | E79: 0.51249947
A80: ConsumerCo | B80: =E45 -> 0.059466667 | C80: 1 | D80: 22.956952 | E80: -1.6410938
A81: FinCo | B81: =F45 -> 0.015566667 | C81: 1 | D81: 12.981144 | E81: -2.6126041
A83: A = sum(u) | B83: =SUM($D$77:$D$81) -> 92.186724
A84: B = mu′u | B84: =SUMPRODUCT($B$77:$B$81,$D$77:$D$81) -> 9.932387
A85: C = mu′v | B85: =SUMPRODUCT($B$77:$B$81,$E$77:$E$81) -> 2.1752816
A86: D = A·C - B² | B86: =B83*B85-B84^2 -> 101.87978
A88: Minimum-Volatility Portfolio (unconstrained, long/short)
B89: TechCo | C89: HealthCo | D89: EnergyCo | E89: ConsumerCo | F89: FinCo
A90: Weight = u_i / A | B90: =D77/$B$83 -> 0.03568289 | C90: =D78/$B$83 -> 0.40481811 | D90: =D79/$B$83 -> 0.16965875 | E90: =D80/$B$83 -> 0.24902665 | F90: =D81/$B$83 -> 0.1408136
A91: Expected Return | B91: =SUMPRODUCT(B90:F90,$B$45:$F$45) -> 0.10774205
A92: Volatility (= sqrt(1/A)) | B92: =SQRT(1/B83) -> 0.10415157
A94: Maximum-Sharpe (Tangency) Portfolio
B95: TechCo | C95: HealthCo | D95: EnergyCo | E95: ConsumerCo | F95: FinCo
A96: t_i = v_i - Rf·u_i (unnormalized) | B96: =E77-$B$68*D77 -> 2.6419142 | C96: =E78-$B$68*D78 -> 9.3261207 | D96: =E79-$B$68*D79 -> -0.14439246 | E96: =E80-$B$68*D80 -> -2.6052858 | F96: =E81-$B$68*D81 -> -3.1578121
A97: Tangency Weight = t_i / Σt | B97: =B96/SUM(B96:F96) -> 0.43592026 | C97: =C96/SUM(B96:F96) -> 1.5388255 | D97: =D96/SUM(B96:F96) -> -0.023824998 | E97: =E96/SUM(B96:F96) -> -0.42987651 | F97: =F96/SUM(B96:F96) -> -0.52104428
A98: Expected Return | B98: =SUMPRODUCT(B97:F97,$B$45:$F$45) -> 0.29009297
A99: Variance | B99: {=MMULT(MMULT(B97:F97,$B$50:$F$54),TRANSPOSE(B97:F97))} -> 0.040935755
A100: Volatility | B100: =SQRT(B99) -> 0.20232586
A101: Sharpe Ratio | B101: =(B98-B68)/B100 -> 1.2262049
A103: Target-Return Portfolio
A104: Target Return (input) | B104: 0.1
A105: λ = (C - B·μ*) / D | B105: =(B85-B84*B104)/B86 -> 0.011602331
A106: γ = (A·μ* - B) / D | B106: =(B83*B104-B84)/B86 -> -0.0070054591
A107: Weight = λ·u_i + γ·v_i | B107: =$B$105*D77+$B$106*E77 -> 0.018690053 | C107: =$B$105*D78+$B$106*E78 -> 0.35667168 | D107: =$B$105*D79+$B$106*E79 -> 0.17787347 | E107: =$B$105*D80+$B$106*E80 -> 0.27785078 | F107: =$B$105*D81+$B$106*E81 -> 0.16891403
A108: Volatility = sqrt((A·μ*² - 2B·μ* + C)/D) | B108: =SQRT((B83*B104^2-2*B84*B104+B85)/B86) -> 0.10441162
A110: Efficient Frontier (closed-form; 15 target-return points)
A111: Target Return | B111: Volatility | C111: Sharpe
A112: =$B$91+(0/14)*(MAX($B$45:$F$45)*1.3-$B$91) -> 0.10774205 | B112: =SQRT((B83*A112^2-2*B84*A112+B85)/B86) -> 0.10415157 | C112: =(A112-$B$68)/B112 -> 0.63121522
A113: =$B$91+(1/14)*(MAX($B$45:$F$45)*1.3-$B$91) -> 0.11562762 | B113: =SQRT((B83*A113^2-2*B84*A113+B85)/B86) -> 0.10442133 | C113: =(A113-$B$68)/B113 -> 0.70510133
A114: =$B$91+(2/14)*(MAX($B$45:$F$45)*1.3-$B$91) -> 0.12351319 | B114: =SQRT((B83*A114^2-2*B84*A114+B85)/B86) -> 0.10522648 | C114: =(A114-$B$68)/B114 -> 0.77464518
A115: =$B$91+(3/14)*(MAX($B$45:$F$45)*1.3-$B$91) -> 0.13139876 | B115: =SQRT((B83*A115^2-2*B84*A115+B85)/B86) -> 0.10655488 | C115: =(A115-$B$68)/B115 -> 0.83899258
A116: =$B$91+(4/14)*(MAX($B$45:$F$45)*1.3-$B$91) -> 0.13928432 | B116: =SQRT((B83*A116^2-2*B84*A116+B85)/B86) -> 0.10838729 | C116: =(A116-$B$68)/B116 -> 0.89756207
A117: =$B$91+(5/14)*(MAX($B$45:$F$45)*1.3-$B$91) -> 0.14716989 | B117: =SQRT((B83*A117^2-2*B84*A117+B85)/B86) -> 0.11069869 | C117: =(A117-$B$68)/B117 -> 0.95005544
A118: =$B$91+(6/14)*(MAX($B$45:$F$45)*1.3-$B$91) -> 0.15505546 | B118: =SQRT((B83*A118^2-2*B84*A118+B85)/B86) -> 0.1134598 | C118: =(A118-$B$68)/B118 -> 0.99643627
A119: =$B$91+(7/14)*(MAX($B$45:$F$45)*1.3-$B$91) -> 0.16294103 | B119: =SQRT((B83*A119^2-2*B84*A119+B85)/B86) -> 0.11663869 | C119: =(A119-$B$68)/B119 -> 1.036886
A120: =$B$91+(8/14)*(MAX($B$45:$F$45)*1.3-$B$91) -> 0.17082659 | B120: =SQRT((B83*A120^2-2*B84*A120+B85)/B86) -> 0.12020223 | C120: =(A120-$B$68)/B120 -> 1.0717488
A121: =$B$91+(9/14)*(MAX($B$45:$F$45)*1.3-$B$91) -> 0.17871216 | B121: =SQRT((B83*A121^2-2*B84*A121+B85)/B86) -> 0.12411727 | C121: =(A121-$B$68)/B121 -> 1.1014757
A122: =$B$91+(10/14)*(MAX($B$45:$F$45)*1.3-$B$91) -> 0.18659773 | B122: =SQRT((B83*A122^2-2*B84*A122+B85)/B86) -> 0.12835168 | C122: =(A122-$B$68)/B122 -> 1.1265745
A123: =$B$91+(11/14)*(MAX($B$45:$F$45)*1.3-$B$91) -> 0.1944833 | B123: =SQRT((B83*A123^2-2*B84*A123+B85)/B86) -> 0.1328749 | C123: =(A123-$B$68)/B123 -> 1.1475704
A124: =$B$91+(12/14)*(MAX($B$45:$F$45)*1.3-$B$91) -> 0.20236886 | B124: =SQRT((B83*A124^2-2*B84*A124+B85)/B86) -> 0.13765848 | C124: =(A124-$B$68)/B124 -> 1.1649763
A125: =$B$91+(13/14)*(MAX($B$45:$F$45)*1.3-$B$91) -> 0.21025443 | B125: =SQRT((B83*A125^2-2*B84*A125+B85)/B86) -> 0.14267624 | C125: =(A125-$B$68)/B125 -> 1.1792744
A126: =$B$91+(14/14)*(MAX($B$45:$F$45)*1.3-$B$91) -> 0.21814 | B126: =SQRT((B83*A126^2-2*B84*A126+B85)/B86) -> 0.14790433 | C126: =(A126-$B$68)/B126 -> 1.1909049
A128: Minimum-Variance Point: | B128: =B92 -> 0.10415157 | C128: =B91 -> 0.10774205 | D128: (vol, ret)
A129: Max-Sharpe (Tangency) Point: | B129: =B100 -> 0.20232586 | C129: =B98 -> 0.29009297 | D129: (vol, ret)
A130: User Portfolio Point: | B130: =B71 -> 0.11371226 | C130: =B69 -> 0.10008667 | D130: (vol, ret)

Sheet Checks
A1: MODEL CHECKS & ERROR FLAGS
A2: Every check should read OK. Any FAIL indicates a broken linkage — locate and fix before relying on outputs.
A4: 1. Balance Sheet Check (Total Assets - Total Liab. & Equity, by year)
B5: FY2023A | C5: FY2024A | D5: FY2025A | E5: FY2026E | F5: FY2027E | G5: FY2028E | H5: FY2029E | I5: FY2030E
A6: Balance Check ($mm) | B6: =Model!B42 -> 0 | C6: =Model!C42 -> 0 | D6: =Model!D42 -> 0 | E6: =Model!E42 -> 0 | F6: =Model!F42 -> 0 | G6: =Model!G42 -> 0 | H6: =Model!H42 -> 0 | I6: =Model!I42 -> 0
A7: Status | B7: =IF(ABS(B6)<0.01,"OK","FAIL") -> OK | C7: =IF(ABS(C6)<0.01,"OK","FAIL") -> OK | D7: =IF(ABS(D6)<0.01,"OK","FAIL") -> OK | E7: =IF(ABS(E6)<0.01,"OK","FAIL") -> OK | F7: =IF(ABS(F6)<0.01,"OK","FAIL") -> OK | G7: =IF(ABS(G6)<0.01,"OK","FAIL") -> OK | H7: =IF(ABS(H6)<0.01,"OK","FAIL") -> OK | I7: =IF(ABS(I6)<0.01,"OK","FAIL") -> OK
A9: 2. Cash Reconciliation (BS Cash = CF Ending Cash, by year)
B10: FY2023A | C10: FY2024A | D10: FY2025A | E10: FY2026E | F10: FY2027E | G10: FY2028E | H10: FY2029E | I10: FY2030E
A11: Difference ($mm) | B11: =Model!B25-Model!B61 -> 0 | C11: =Model!C25-Model!C61 -> 0 | D11: =Model!D25-Model!D61 -> 0 | E11: =Model!E25-Model!E61 -> 0 | F11: =Model!F25-Model!F61 -> 0 | G11: =Model!G25-Model!G61 -> 0 | H11: =Model!H25-Model!H61 -> 0 | I11: =Model!I25-Model!I61 -> 0
A12: Status | B12: =IF(ABS(B11)<0.01,"OK","FAIL") -> OK | C12: =IF(ABS(C11)<0.01,"OK","FAIL") -> OK | D12: =IF(ABS(D11)<0.01,"OK","FAIL") -> OK | E12: =IF(ABS(E11)<0.01,"OK","FAIL") -> OK | F12: =IF(ABS(F11)<0.01,"OK","FAIL") -> OK | G12: =IF(ABS(G11)<0.01,"OK","FAIL") -> OK | H12: =IF(ABS(H11)<0.01,"OK","FAIL") -> OK | I12: =IF(ABS(I11)<0.01,"OK","FAIL") -> OK
A14: 3. Retained Earnings Roll-Forward Check
A15: RE(t) = RE(t-1) + NI(t) - Dividends(t) — verified by construction; recomputed independently here.
B16: FY2023A | C16: FY2024A | D16: FY2025A | E16: FY2026E | F16: FY2027E | G16: FY2028E | H16: FY2029E | I16: FY2030E
A17: Independent Recompute Diff | B17: =Model!B39-(Assumptions!$B$22+Model!B19-Model!B20) -> 0 | C17: =Model!C39-(Model!B39+Model!C19-Model!C20) -> 0 | D17: =Model!D39-(Model!C39+Model!D19-Model!D20) -> 0 | E17: =Model!E39-(Model!D39+Model!E19-Model!E20) -> 0 | F17: =Model!F39-(Model!E39+Model!F19-Model!F20) -> 0 | G17: =Model!G39-(Model!F39+Model!G19-Model!G20) -> 0 | H17: =Model!H39-(Model!G39+Model!H19-Model!H20) -> 0 | I17: =Model!I39-(Model!H39+Model!I19-Model!I20) -> 0
A18: Status | B18: =IF(ABS(B17)<0.01,"OK","FAIL") -> OK | C18: =IF(ABS(C17)<0.01,"OK","FAIL") -> OK | D18: =IF(ABS(D17)<0.01,"OK","FAIL") -> OK | E18: =IF(ABS(E17)<0.01,"OK","FAIL") -> OK | F18: =IF(ABS(F17)<0.01,"OK","FAIL") -> OK | G18: =IF(ABS(G17)<0.01,"OK","FAIL") -> OK | H18: =IF(ABS(H17)<0.01,"OK","FAIL") -> OK | I18: =IF(ABS(I17)<0.01,"OK","FAIL") -> OK
A20: 4. Debt Roll-Forward Check (LT Debt(t) = LT Debt(t-1) + Issuance)
B21: FY2023A | C21: FY2024A | D21: FY2025A | E21: FY2026E | F21: FY2027E | G21: FY2028E | H21: FY2029E | I21: FY2030E
A22: Difference | B22: =Model!B35-(Assumptions!$B$24+Model!B56) -> 0 | C22: =Model!C35-(Model!B35+Model!C56) -> 0 | D22: =Model!D35-(Model!C35+Model!D56) -> 0 | E22: =Model!E35-(Model!D35+Model!E56) -> 0 | F22: =Model!F35-(Model!E35+Model!F56) -> 0 | G22: =Model!G35-(Model!F35+Model!G56) -> 0 | H22: =Model!H35-(Model!G35+Model!H56) -> 0 | I22: =Model!I35-(Model!H35+Model!I56) -> 0
A23: Status | B23: =IF(ABS(B22)<0.01,"OK","FAIL") -> OK | C23: =IF(ABS(C22)<0.01,"OK","FAIL") -> OK | D23: =IF(ABS(D22)<0.01,"OK","FAIL") -> OK | E23: =IF(ABS(E22)<0.01,"OK","FAIL") -> OK | F23: =IF(ABS(F22)<0.01,"OK","FAIL") -> OK | G23: =IF(ABS(G22)<0.01,"OK","FAIL") -> OK | H23: =IF(ABS(H22)<0.01,"OK","FAIL") -> OK | I23: =IF(ABS(I22)<0.01,"OK","FAIL") -> OK
A25: 5. DCF Integrity Checks
A26: Enterprise Value = Sum PV(FCFF) + PV(Terminal Value)? (Gordon) | B26: =DCF!B37-(DCF!B23+DCF!B29) -> 0 | C26: =IF(ABS(B26)<0.01,"OK","FAIL") -> OK
A27: Terminal Growth < WACC? (required for Gordon Growth to be valid) | B27: =IF(DCF!B26<DCF!B14,"OK","FAIL - g >= WACC") -> OK
A28: Equity Value = Implied Price × Shares? | B28: =DCF!B42*DCF!B41-DCF!B40 -> 0 | C28: =IF(ABS(B28)<0.01,"OK","FAIL") -> OK
A30: 6. Portfolio Checks
A31: Sum of User Portfolio Weights = 100%? | B31: =IF(ABS(Portfolio!B67-1)<0.001,"OK","FAIL") -> OK
A32: Portfolio Return Independent Recompute Diff | B32: =Portfolio!B69-SUMPRODUCT(Portfolio!B66:F66,Portfolio!B45:F45) -> 0
A33: Min-Variance Weights Sum to 100%? | B33: =IF(ABS(SUM(Portfolio!B90:F90)-1)<0.001,"OK","FAIL") -> OK
A34: Tangency Weights Sum to 100%? | B34: =IF(ABS(SUM(Portfolio!B97:F97)-1)<0.001,"OK","FAIL") -> OK
A36: Summary — All Checks
A37: If every status cell above reads OK, the workbook is internally consistent and ready to use.
